binscatter/.DS_Store
binscatter/__init__.py
binscatter/core.py
binscatter-0.2.0.dist-info/WHEEL
binscatter-0.2.0.dist-info/METADATA
binscatter-0.2.0.dist-info/RECORD
