Metadata-Version: 2.3
Name: binscatter
Version: 0.2.0
Summary: Cross-backend binscatter plots.
Keywords: binscatter,visualization,econometrics
Author: Matthias Kaeding
License: MIT License
Classifier: Development Status :: 3 - Alpha
Classifier: Intended Audience :: Science/Research
Classifier: License :: OSI Approved :: MIT License
Classifier: Programming Language :: Python :: 3 :: Only
Classifier: Programming Language :: Python :: 3.11
Classifier: Topic :: Scientific/Engineering :: Visualization
Requires-Dist: narwhals>=2.1.2
Requires-Dist: numpy>=2.3
Requires-Dist: plotly>=6.3.0
Requires-Python: >=3.11
Project-URL: homepage, https://github.com/matthiaskaeding/binscatter
Project-URL: issues, https://github.com/matthiaskaeding/binscatter/issues
Project-URL: repository, https://github.com/matthiaskaeding/binscatter
